acc_tariff/__init__.py
acc_tariff/_logger.py
acc_tariff/_version.py
acc_tariff-1.0.3.dist-info/METADATA
acc_tariff-1.0.3.dist-info/WHEEL
acc_tariff-1.0.3.dist-info/top_level.txt
acc_tariff-1.0.3.dist-info/RECORD
