Metadata-Version: 2.4
Name: acc_tariff
Version: 1.0.3
Summary: Make IMPORT Great Again!
Author-email: dboyliao <qmalliao@gmail.com>
Project-URL: Homepage, https://github.com/dboyliao/acc_tariff
Classifier: Programming Language :: Python :: 3
Requires-Python: >=3.11
